README.md
setup.cfg
setup.py
useless_lib/__init__.py
useless_lib/killable_thread.py
useless_lib/useful.py
useless_lib.egg-info/PKG-INFO
useless_lib.egg-info/SOURCES.txt
useless_lib.egg-info/dependency_links.txt
useless_lib.egg-info/top_level.txt