Metadata-Version: 1.1
Name: useless-lib
Version: 1.0.0
Summary: ...
Home-page: https://github.com/1Gregory/useless-lib.git
Author: Andreew Gregory
Author-email: grinadand@gmail.com
License: MIT
Download-URL: https://github.com/1Gregory/useless-lib/archive/1.0.0.tar.gz
Keywords: useless
Platform: UNKNOWN
